MANIFEST.in
README.rst
setup.py
kita/__init__.py
kita/hooks.py
kita/addon/.mrbob.ini
kita/addon/+addon.name+/README.rst.oca.bob
kita/addon/+addon.name+/__init__.py
kita/addon/+addon.name+/__openerp__.py.bob
kita/addon/+addon.name+/static/description/icon.png.oca
kita/model/.mrbob.ini
kita/model/demo/+model.name_underscored+.xml.bob
kita/model/models/+model.name_underscored+.py.bob
kita/model/security/+model.name_underscored+.xml.bob
kita/model/views/+model.name_underscored+.xml.bob
kita/test/.mrbob.ini
kita/test/tests/+test.name_underscored+.py.bob
kita/wizard/.mrbob.ini
kita/wizard/wizards/+wizard.name_underscored+.py.bob
kita/wizard/wizards/+wizard.name_underscored+.xml.bob
mrbob.kita.egg-info/PKG-INFO
mrbob.kita.egg-info/SOURCES.txt
mrbob.kita.egg-info/dependency_links.txt
mrbob.kita.egg-info/requires.txt
mrbob.kita.egg-info/top_level.txt