Metadata-Version: 1.1
Name: mrbob.kita
Version: 1.5
Summary: mr.bob templates for kitayazilim's Odoo projects
Home-page: UNKNOWN
Author: kitayazilim.com
Author-email: info@kitayazilim.com
License: LGPLv3
Platform: UNKNOWN
Classifier: Intended Audience :: Developers
Classifier: License :: OSI Approved :: GNU Affero General Public License v3 or later (AGPLv3+)
Classifier: Operating System :: OS Independent
Classifier: Programming Language :: Python
Classifier: Framework :: Odoo
